{
  "data": {
    "ServiceFilterValues": [
      {
        "displayName": "Category",
        "filterName": "category",
        "values": ["Finance", "Health", "Education"],
        "__typename": "FilterItem"
      },
      {
        "displayName": "Status",
        "filterName": "status",
        "values": ["Active", "Inactive", "Pending"],
        "__typename": "FilterItem"
      },
      {
        "displayName": "Region",
        "filterName": "region",
        "values": ["North America", "Europe", "Asia"],
        "__typename": "FilterItem"
      }
    ],
    "__typename": "GetServiceFiltersQuery"
  }
}
